{
  "project_info": {
    "project_number": "969381679953",
    "firebase_url": "https://mundihome-bf35f-default-rtdb.firebaseio.com",
    "project_id": "mundihome-bf35f",
    "storage_bucket": "mundihome-bf35f.firebasestorage.app"
  },
  "client": [
    {
      "client_info": {
        "mobilesdk_app_id": "1:969381679953:android:1903ff7d5b43419beab970",
        "android_client_info": {
          "package_name": "com.mh.mundihome"
        }
      },
      "oauth_client": [
        {
          "client_id": "969381679953-j2qr348lnnts5umj44sc9req064d79lu.apps.googleusercontent.com",
          "client_type": 1,
          "android_info": {
            "package_name": "com.mh.mundihome",
            "certificate_hash": "cf6522b6eff55cf05825e91caebdff2bca0694c8"
          }
        },
        {
          "client_id": "969381679953-k2nr0npi90v27bfqptakgle8j3j6pe8t.apps.googleusercontent.com",
          "client_type": 3
        }
      ],
      "api_key": [
        {
          "current_key": "AIzaSyB4Y0uBCQGLUggIgr_kpeAeBN2OgmWliv8"
        }
      ],
      "services": {
        "appinvite_service": {
          "other_platform_oauth_client": [
            {
              "client_id": "969381679953-k2nr0npi90v27bfqptakgle8j3j6pe8t.apps.googleusercontent.com",
              "client_type": 3
            }
          ]
        }
      }
    }
  ],
  "configuration_version": "1"
}